Binning_refiner/Binning_refiner_config.py
Binning_refiner/VERSION
Binning_refiner/__init__.py
Binning_refiner/get_sankey_plot.R
Binning_refiner-1.4.3.data/scripts/Binning_refiner
Binning_refiner-1.4.3.dist-info/LICENSE.txt
Binning_refiner-1.4.3.dist-info/METADATA
Binning_refiner-1.4.3.dist-info/WHEEL
Binning_refiner-1.4.3.dist-info/top_level.txt
Binning_refiner-1.4.3.dist-info/RECORD
