Metadata-Version: 1.0
Name: Binning_refiner
Version: 1.4.3
Summary: Binning_refiner
Home-page: https://github.com/songweizhi/Binning_refiner
Author: Weizhi Song, Torsten Thomas
Author-email: songwz03@gmail.com
License: GPL3+
Keywords: Bioinformatics Metagenomics Binning Refinement
Platform: UNKNOWN
